uselib/__init__.py
uselib/files.py
uselib-1.0.0.dist-info/LICENSE
uselib-1.0.0.dist-info/METADATA
uselib-1.0.0.dist-info/WHEEL
uselib-1.0.0.dist-info/top_level.txt
uselib-1.0.0.dist-info/RECORD
