Metadata-Version: 2.1
Name: uselib
Version: 1.0.0
Summary: Библиотека с полезными и часто используемыми функциями
Author-email: Vladislav117 <siluetkysta@gmail.com>
Project-URL: Homepage, https://github.com/Vladislav117/uselib
Project-URL: Issues, https://github.com/Vladislav117/uselib/issues
Classifier: Programming Language :: Python :: 3
Classifier: License :: OSI Approved :: MIT License
Classifier: Operating System :: OS Independent
Requires-Python: >=3.6
License-File: LICENSE
